{
  "version": "1.0",
  "id": "Vesta 1.6 IM",
  "displayName": "",
  "manual": {
    "description": "Калибровка двигателя Vesta 1.6 IM для летних условий",
    "client": "АвтоВАЗ",
    "tags": [
      "vesta",
      "production",
      "summer"
    ],
    "status": "active",
    "notes": "Базовая калибровка с оптимизацией топливной экономичности. Тестирование на стенде завершено 15.10.2025.",
    "color": "#3b82f6"
  },
  "created": "2025-10-15T10:30:00.000Z",
  "modified": "2025-10-22T07:50:00.000Z"
}